alt_side_parking/__init__.py
alt_side_parking/config.py
alt_side_parking/feed.py
alt_side_parking/sms.py
alt_side_parking/test_mocks.py
alt_side_parking/__pycache__/__init__.cpython-37.pyc
alt_side_parking/__pycache__/config.cpython-37.pyc
alt_side_parking/__pycache__/feed.cpython-37.pyc
alt_side_parking/scripts/reminder.py
alt_side_parking-1.0.dist-info/METADATA
alt_side_parking-1.0.dist-info/WHEEL
alt_side_parking-1.0.dist-info/entry_points.txt
alt_side_parking-1.0.dist-info/top_level.txt
alt_side_parking-1.0.dist-info/RECORD
