Metadata-Version: 2.1
Name: alt-side-parking
Version: 1.0
Summary: UNKNOWN
Home-page: UNKNOWN
Author: Salah Ahmed
Author-email: salahs.email@pm.me
License: UNKNOWN
Keywords: python
Platform: UNKNOWN
Classifier: Programming Language :: Python
Classifier: License :: OSI Approved :: MIT License
Requires-Dist: arrow
Requires-Dist: phonenumbers
Requires-Dist: structlog
Requires-Dist: twilio
Requires-Dist: salahs-twitterbot (<2.0,>=1.3.0)
Provides-Extra: dev
Requires-Dist: automock ; extra == 'dev'
Requires-Dist: coverage[toml] ; extra == 'dev'
Requires-Dist: pytest-cov ; extra == 'dev'
Requires-Dist: pytest-freezegun ; extra == 'dev'
Requires-Dist: black ; extra == 'dev'
Requires-Dist: flake8 ; extra == 'dev'
Requires-Dist: ipython ; extra == 'dev'
Requires-Dist: pdbpp ; extra == 'dev'
Requires-Dist: pre-commit ; extra == 'dev'
Requires-Dist: tox ; extra == 'dev'
Provides-Extra: test
Requires-Dist: automock ; extra == 'test'
Requires-Dist: coverage[toml] ; extra == 'test'
Requires-Dist: pytest-cov ; extra == 'test'
Requires-Dist: pytest-freezegun ; extra == 'test'
